MANIFEST.in
README.rst
bootstrap.py
setup.cfg
setup.py
collective/__init__.py
collective.geo.json.egg-info/PKG-INFO
collective.geo.json.egg-info/SOURCES.txt
collective.geo.json.egg-info/dependency_links.txt
collective.geo.json.egg-info/entry_points.txt
collective.geo.json.egg-info/namespace_packages.txt
collective.geo.json.egg-info/not-zip-safe
collective.geo.json.egg-info/requires.txt
collective.geo.json.egg-info/top_level.txt
collective/geo/__init__.py
collective/geo/json/__init__.py
collective/geo/json/configure.zcml
collective/geo/json/interfaces.py
collective/geo/json/testing.py
collective/geo/json/browser/__init__.py
collective/geo/json/browser/configure.zcml
collective/geo/json/browser/jsonview.py
collective/geo/json/profiles/default/browserlayer.xml
collective/geo/json/profiles/default/metadata.xml
collective/geo/json/tests/__init__.py
collective/geo/json/tests/test_collection.py
collective/geo/json/tests/test_document.py
collective/geo/json/tests/test_folder.py
collective/geo/json/tests/test_install.py
docs/HISTORY.txt
docs/INSTALL.txt
docs/LICENSE.GPL
docs/LICENSE.txt