Metadata-Version: 1.1
Name: collective.geo.json
Version: 0.4.1
Summary: Collective Geo GeoJson output
Home-page: https://github.com/collective/collective.geo.json
Author: Christian Ledermann
Author-email: christian.ledermann@gmail.com
License: GPL
Keywords: GIS JSON
Platform: UNKNOWN
Classifier: Framework :: Plone
Classifier: Programming Language :: Python
Classifier: Topic :: Software Development :: Libraries :: Python Modules
Classifier: Framework :: Plone :: 4.0
Classifier: Framework :: Plone :: 4.1
Classifier: Framework :: Plone :: 4.2
Classifier: Development Status :: 4 - Beta
Classifier: Operating System :: OS Independent
